tinker/__init__.py
tinker/_base_client.py
tinker/_client.py
tinker/_compat.py
tinker/_constants.py
tinker/_exceptions.py
tinker/_files.py
tinker/_models.py
tinker/_qs.py
tinker/_resource.py
tinker/_response.py
tinker/_streaming.py
tinker/_types.py
tinker/_version.py
tinker/py.typed
tinker/_utils/__init__.py
tinker/_utils/_logs.py
tinker/_utils/_proxy.py
tinker/_utils/_reflection.py
tinker/_utils/_resources_proxy.py
tinker/_utils/_streams.py
tinker/_utils/_sync.py
tinker/_utils/_transform.py
tinker/_utils/_typing.py
tinker/_utils/_utils.py
tinker/cli/CLAUDE.md
tinker/cli/__main__.py
tinker/cli/client.py
tinker/cli/context.py
tinker/cli/exceptions.py
tinker/cli/lazy_group.py
tinker/cli/output.py
tinker/cli/commands/__init__.py
tinker/cli/commands/checkpoint.py
tinker/cli/commands/run.py
tinker/cli/commands/version.py
tinker/lib/api_future_impl.py
tinker/lib/async_tinker_provider.py
tinker/lib/chunked_fwdbwd_helpers.py
tinker/lib/client_connection_pool_type.py
tinker/lib/internal_client_holder.py
tinker/lib/queue_state_logger.py
tinker/lib/retry_handler.py
tinker/lib/retryable_exception.py
tinker/lib/sync_only.py
tinker/lib/telemetry.py
tinker/lib/telemetry_provider.py
tinker/lib/telemetry_test.py
tinker/lib/public_interfaces/__init__.py
tinker/lib/public_interfaces/api_future.py
tinker/lib/public_interfaces/rest_client.py
tinker/lib/public_interfaces/sampling_client.py
tinker/lib/public_interfaces/service_client.py
tinker/lib/public_interfaces/training_client.py
tinker/resources/__init__.py
tinker/resources/futures.py
tinker/resources/models.py
tinker/resources/sampling.py
tinker/resources/service.py
tinker/resources/telemetry.py
tinker/resources/training.py
tinker/resources/weights.py
tinker/types/__init__.py
tinker/types/checkpoint.py
tinker/types/checkpoint_archive_url_response.py
tinker/types/checkpoints_list_response.py
tinker/types/create_model_request.py
tinker/types/create_model_response.py
tinker/types/create_sampling_session_request.py
tinker-0.10.0.dist-info/METADATA
tinker-0.10.0.dist-info/WHEEL
tinker-0.10.0.dist-info/entry_points.txt
tinker-0.10.0.dist-info/licenses/LICENSE
tinker-0.10.0.dist-info/RECORD
